kpi_calculator-0.2.0.dist-info/licenses/LICENSE
kpicalculator/__init__.py
kpicalculator/api.py
kpicalculator/exceptions.py
kpicalculator/kpi_manager.py
kpicalculator/py.typed
kpicalculator/adapters/__init__.py
kpicalculator/adapters/base_adapter.py
kpicalculator/adapters/common_model.py
kpicalculator/adapters/database_time_series_loader.py
kpicalculator/adapters/esdl_adapter.py
kpicalculator/adapters/time_series_manager.py
kpicalculator/adapters/time_series_protocols.py
kpicalculator/adapters/xml_time_series_adapter.py
kpicalculator/calculators/__calculators__.py
kpicalculator/calculators/cost_calculator.py
kpicalculator/calculators/emission_calculator.py
kpicalculator/calculators/energy_calculator.py
kpicalculator/common/__init__.py
kpicalculator/common/constants.py
kpicalculator/common/logging_utils.py
kpicalculator/common/types.py
kpicalculator/reporting/__init__.py
kpicalculator/reporting/base_exporter.py
kpicalculator/reporting/esdl_kpi_exporter.py
kpicalculator/security/__init__.py
kpicalculator/security/credential_manager.py
kpicalculator/security/input_validator.py
kpi_calculator-0.2.0.dist-info/METADATA
kpi_calculator-0.2.0.dist-info/WHEEL
kpi_calculator-0.2.0.dist-info/entry_points.txt
kpi_calculator-0.2.0.dist-info/top_level.txt
kpi_calculator-0.2.0.dist-info/RECORD
