Metadata-Version: 2.4
Name: kpi-calculator
Version: 0.2.0
Summary: Extend ESDL's with relevant key performance indicators.
Author-email: Jesús Andrés Rodríguez Sarasty <jesusandres.rodriguez@deltares.nl>
Project-URL: homepage, https://www.nwn.nu
Project-URL: documentation, https://readthedocs.org
Project-URL: repository, https://github.com/Nieuwe-Warmte-Nu/kpi-calculator
Project-URL: changelog, https://github.com/Nieuwe-Warmte-Nu/kpi-calculator/blob/main/CHANGELOG.md
Classifier: License :: OSI Approved :: GNU General Public License v3 (GPLv3)
Classifier: Programming Language :: Python :: 3
Classifier: Programming Language :: Python :: 3.11
Classifier: Operating System :: OS Independent
Classifier: Development Status :: 4 - Beta
Classifier: Intended Audience :: Developers
Classifier: Intended Audience :: Science/Research
Classifier: Intended Audience :: Information Technology
Classifier: Topic :: Scientific/Engineering
Classifier: Topic :: Scientific/Engineering :: Mathematics
Classifier: Topic :: Scientific/Engineering :: Physics
Requires-Python: >=3.11
License-File: LICENSE
Requires-Dist: coloredlogs~=15.0.1
Requires-Dist: numpy<3.0,>=2.1.0
Requires-Dist: pandas<3.0,>=2.2.2
Requires-Dist: pandas-stubs
Requires-Dist: pyesdl~=25.7
Requires-Dist: xmltodict==0.14.2
Requires-Dist: types-xmltodict
Requires-Dist: influxdb>=5.3.2
Requires-Dist: pydantic<3.0,>=2.0.0
Requires-Dist: urllib3>=2.6.3
Requires-Dist: filelock>=3.20.1
Dynamic: license-file
